{
  "posts": [
    {
      "title": "신규데이터",
      "content": "데이터입니다. @@@@  dddd ㅀㅀㄹ",
      "id": 10
    },
    {
      "title": "아무거",
      "content": "나 쓰자고",
      "createdAt": 1735621967243,
      "id": 11
    },
    {
      "title": "폼 글쓰기",
      "content": "폼글글써보기",
      "createdAt": 1735697830397,
      "id": 12
    },
    {
      "title": "테스트",
      "content": "테스트입니다",
      "createdAt": 1735698445616,
      "id": 13
    },
    {
      "title": "제목1",
      "content": "내용1fffㅇㅇㅇㅁㅇㅇㅇ",
      "createdAt": 1735699931171,
      "id": 14
    }
  ]
}